odoo/addons/sale_confirm_group/README.rst
odoo/addons/sale_confirm_group/__init__.py
odoo/addons/sale_confirm_group/__manifest__.py
odoo/addons/sale_confirm_group/i18n/sale_confirm_group.pot
odoo/addons/sale_confirm_group/models/__init__.py
odoo/addons/sale_confirm_group/models/res_company.py
odoo/addons/sale_confirm_group/models/sale_order.py
odoo/addons/sale_confirm_group/readme/CONFIGURE.md
odoo/addons/sale_confirm_group/readme/CONTRIBUTORS.md
odoo/addons/sale_confirm_group/readme/DESCRIPTION.md
odoo/addons/sale_confirm_group/static/description/icon.png
odoo/addons/sale_confirm_group/static/description/index.html
odoo/addons/sale_confirm_group/tests/__init__.py
odoo/addons/sale_confirm_group/tests/common.py
odoo/addons/sale_confirm_group/tests/test_sale_confirm_group.py
odoo/addons/sale_confirm_group/wizards/__init__.py
odoo/addons/sale_confirm_group/wizards/res_config_settings.py
odoo/addons/sale_confirm_group/wizards/res_config_settings.xml
odoo_addon_sale_confirm_group-18.0.1.0.0.3.dist-info/METADATA
odoo_addon_sale_confirm_group-18.0.1.0.0.3.dist-info/WHEEL
odoo_addon_sale_confirm_group-18.0.1.0.0.3.dist-info/top_level.txt
odoo_addon_sale_confirm_group-18.0.1.0.0.3.dist-info/RECORD
